aklauncher/__init__.py
aklauncher/core.py
aklauncher-0.1.1.dist-info/METADATA
aklauncher-0.1.1.dist-info/WHEEL
aklauncher-0.1.1.dist-info/top_level.txt
aklauncher-0.1.1.dist-info/RECORD
