Metadata-Version: 2.4
Name: aklauncher
Version: 0.1.1
Summary: Simple Windows-only launcher that opens multiple Python scripts in separate CMD windows.
Author: Akshay Ajit Bhawar
Requires-Python: >=3.6
Dynamic: author
Dynamic: requires-python
Dynamic: summary
